sane/__init__.py
sane/action.py
sane/action_launcher.py
sane/dag.py
sane/dagvis.py
sane/env_from_script.sh
sane/environment.py
sane/helpers.py
sane/host.py
sane/hpc_host.py
sane/logger.py
sane/match.py
sane/options.py
sane/orchestrator.py
sane/resources.py
sane/sane_runner.py
sane/sane_view.py
sane/save_state.py
sane/user_space.py
sane/utdict.py
sane_workflows-1.0.0.dist-info/licenses/LICENSE
sane_workflows-1.0.0.dist-info/METADATA
sane_workflows-1.0.0.dist-info/WHEEL
sane_workflows-1.0.0.dist-info/entry_points.txt
sane_workflows-1.0.0.dist-info/top_level.txt
sane_workflows-1.0.0.dist-info/RECORD
