Metadata-Version: 2.4
Name: sane-workflows
Version: 1.0.0
Summary: Simple Action 'n Environment Workflows
Author-email: Anthony Islas <aislas@ucar.edu>
License-Expression: MIT
Project-URL: Repository, https://github.com/islas/sane_workflows.git
Project-URL: Issues, https://github.com/islas/sane_workflows/issues
Keywords: sane,workflow,dag,orchestration
Classifier: Development Status :: 4 - Beta
Classifier: Intended Audience :: Developers
Classifier: Topic :: Software Development :: Testing
Classifier: Programming Language :: Python :: 3.6
Classifier: Programming Language :: Python :: 3.7
Classifier: Programming Language :: Python :: 3.8
Classifier: Programming Language :: Python :: 3.9
Classifier: Programming Language :: Python :: 3.10
Classifier: Programming Language :: Python :: 3.11
Classifier: Programming Language :: Python :: 3.12
Classifier: Programming Language :: Python :: 3.13
Requires-Python: >=3.6
License-File: LICENSE
Dynamic: license-file
